LICENSE
MANIFEST.in
README.rst
setup.py
isotopic_logging/__init__.py
isotopic_logging/concurrency.py
isotopic_logging/context.py
isotopic_logging/defaults.py
isotopic_logging/generators.py
isotopic_logging/injectors.py
isotopic_logging/logger.py
isotopic_logging/prefix.py
isotopic_logging/proxy.py
isotopic_logging.egg-info/PKG-INFO
isotopic_logging.egg-info/SOURCES.txt
isotopic_logging.egg-info/dependency_links.txt
isotopic_logging.egg-info/not-zip-safe
isotopic_logging.egg-info/pbr.json
isotopic_logging.egg-info/top_level.txt