Metadata-Version: 1.1
Name: isotopic-logging
Version: 2.0.0
Summary: Mark and trace events in your log alike isotopic labeling
Home-page: https://github.com/oblalex/isotopic-logging
Author: Alexander Oblovatniy
Author-email: oblovatniy@gmail.com
License: LGPLv3
Keywords: library,logging
Platform: any
Classifier: Development Status :: 5 - Production/Stable
Classifier: Intended Audience :: Developers
Classifier: License :: OSI Approved :: GNU Lesser General Public License v3 (LGPLv3)
Classifier: Natural Language :: English
Classifier: Operating System :: OS Independent
Classifier: Programming Language :: Python :: 2.7
Classifier: Programming Language :: Python :: 3.4
Classifier: Topic :: Software Development :: Libraries :: Python Modules
